scim2_models/__init__.py
scim2_models/annotations.py
scim2_models/attributes.py
scim2_models/base.py
scim2_models/constants.py
scim2_models/context.py
scim2_models/exceptions.py
scim2_models/messages/__init__.py
scim2_models/messages/bulk.py
scim2_models/messages/error.py
scim2_models/messages/list_response.py
scim2_models/messages/message.py
scim2_models/messages/patch_op.py
scim2_models/messages/search_request.py
scim2_models/path.py
scim2_models/py.typed
scim2_models/reference.py
scim2_models/resources/__init__.py
scim2_models/resources/enterprise_user.py
scim2_models/resources/group.py
scim2_models/resources/resource.py
scim2_models/resources/resource_type.py
scim2_models/resources/schema.py
scim2_models/resources/service_provider_config.py
scim2_models/resources/user.py
scim2_models/scim_object.py
scim2_models/utils.py
scim2_models-0.6.3.dist-info/WHEEL
scim2_models-0.6.3.dist-info/METADATA
scim2_models-0.6.3.dist-info/RECORD
