Metadata-Version: 2.3
Name: scim2-models
Version: 0.6.3
Summary: SCIM2 models serialization and validation with pydantic
Keywords: scim,scim2,provisioning,pydantic,rfc7643,rfc7644
Author: Yaal Coop
Author-email: Yaal Coop <contact@yaal.coop>
License:                                  Apache License
Classifier: Intended Audience :: Developers
Classifier: Development Status :: 3 - Alpha
Classifier: Programming Language :: Python :: 3.9
Classifier: Programming Language :: Python :: 3.10
Classifier: Programming Language :: Python :: 3.11
Classifier: Programming Language :: Python :: 3.12
Classifier: Programming Language :: Python :: 3.13
Classifier: Programming Language :: Python :: Implementation :: CPython
Classifier: License :: OSI Approved :: Apache Software License
Classifier: Environment :: Web Environment
Classifier: Programming Language :: Python
Classifier: Operating System :: OS Independent
Requires-Dist: pydantic[email]>=2.12.0
Requires-Python: >=3.10
Project-URL: changelog, https://scim2-models.readthedocs.io/en/latest/changelog.html
Project-URL: documentation, https://scim2-models.readthedocs.io
Project-URL: funding, https://github.com/sponsors/python-scim
Project-URL: repository, https://github.com/python-scim/scim2-models
